rvm_valve/__init__.py
rvm_valve/rvm_valve.py
rvm_valve-1.0.0.dist-info/LICENSE
rvm_valve-1.0.0.dist-info/METADATA
rvm_valve-1.0.0.dist-info/WHEEL
rvm_valve-1.0.0.dist-info/top_level.txt
rvm_valve-1.0.0.dist-info/RECORD
