Metadata-Version: 2.1
Name: rvm_valve
Version: 1.0.0
Summary: Python driver for the Advanced Microfluidics OEM AVM rotary valve. 
Author-email: "Tobias E. Naegele" <github@tobiasnaegele.com>
License: Apache License
Project-URL: Homepage, https://github.com/tnaegele/rvm_valve
Project-URL: Issues, https://github.com/tnaegele/rvm_valve/issues
Classifier: Programming Language :: Python :: 3
Classifier: License :: OSI Approved :: Apache Software License
Classifier: Operating System :: OS Independent
Requires-Python: >=3.8
License-File: LICENSE
Requires-Dist: pyserial ==3.5
